{
  "uid": "Duis nostrud irure anim",
  "name": "Excepteur tempor",
  "type": "sed dolor",
  "domain": {
    "domain-type": "eu nisi sint",
    "uid": "ullamco",
    "name": "adipisicing dolor"
  },
  "meta-info": {
    "lock": "elit in dolor non nisi",
    "validation-state": "sed quis",
    "last-modify-time": {
      "posix": 16873769,
      "iso-8601": "irure sed"
    },
    "last-modifier": "exercitation dolor sit non",
    "creation-time": {
      "posix": 8323580,
      "iso-8601": "fugiat voluptate ullamco"
    },
    "creator": "veniam ut sit dolore consequat"
  },
  "tags": [],
  "read-only": true,
  "comments": "adipi",
  "color": "nostrud quis voluptate adipisicing ex",
  "icon": "quis non dolore"
}